daco/__init__.py
daco-0.0.0.dist-info/METADATA
daco-0.0.0.dist-info/WHEEL
daco-0.0.0.dist-info/RECORD
