Metadata-Version: 2.1
Name: daco
Version: 0.0.0
Summary: Coming soon!
Author: Daco
Author-email: support@daco.sh
Requires-Python: >=3.11,<4.0
Classifier: Programming Language :: Python :: 3
Classifier: Programming Language :: Python :: 3.11
Classifier: Programming Language :: Python :: 3.12
